{
  "abilities": [
    {
      "abilityID": "",
      "abilityName": "Avatar_SkirkNew_NormalAttack",
      "abilityOverride": ""
    },
    {
      "abilityID": "",
      "abilityName": "Avatar_SkirkNew_ExtraAttack",
      "abilityOverride": ""
    },
       {
      "abilityID": "",
      "abilityName": "Avatar_SkirkNew_NormalAttack_DamageHandler",
      "abilityOverride": ""
    },
    {
      "abilityID": "",
      "abilityName": "Avatar_SkirkNew_ElementalArt_HoverAir",
      "abilityOverride": ""
    },
     {
      "abilityID": "",
      "abilityName": "Avatar_SkirkNew_ElementalArt_HoverAir_ExtraAttack",
      "abilityOverride": ""
    },
     {
      "abilityID": "",
      "abilityName": "Avatar_SkirkNew_ElementalArt_InHoverAir",
      "abilityOverride": ""
    },
      {
      "abilityID": "",
      "abilityName": "Avatar_SkirkNew_EnterHoverAir",
      "abilityOverride": ""
    },
    {
      "abilityID": "",
      "abilityName": "Avatar_SkirkNew_ExitHoverAir",
      "abilityOverride": ""
    },
    {
      "abilityID": "",
      "abilityName": "Avatar_SkirkNew_ElementalArt_Dash",
      "abilityOverride": ""
    },
        {
      "abilityID": "",
      "abilityName": "Avatar_SkirkNew_ElementalArt_Dash_ExtraAttack",
      "abilityOverride": ""
    },
       {
      "abilityID": "",
      "abilityName": "Avatar_SkirkNew_NyxCycle",
      "abilityOverride": ""
    },
        {
      "abilityID": "",
      "abilityName": "Avatar_SkirkNew_NyxState_Attack",
      "abilityOverride": ""
    },
     {
      "abilityID": "",
      "abilityName": "Avatar_SkirkNew_NyxSwitch_ExitButton",
      "abilityOverride": ""
    },
        {
      "abilityID": "",
      "abilityName": "Avatar_SkirkNew_ElementalArt_Exit",
      "abilityOverride": ""
    },
    {
      "abilityID": "",
      "abilityName": "Avatar_SkirkNew_ElementalArt_ExitButton",
      "abilityOverride": ""
    },
    {
      "abilityID": "",
      "abilityName": "Avatar_SkirkNew_ElementalBurst",
      "abilityOverride": ""
    },
       {
      "abilityID": "",
      "abilityName": "Avatar_SkirkNew_ElementalBurst_DamageHandler",
      "abilityOverride": ""
    },
      {
      "abilityID": "",
      "abilityName": "Avatar_SkirkNew_DamageHandler",
      "abilityOverride": ""
    },
    {
      "abilityID": "",
      "abilityName": "Avatar_SkirkNew_FallingAnthem",
      "abilityOverride": ""
    },
    {
      "abilityID": "",
      "abilityName": "Avatar_SkirkNew_Misc_Handler",
      "abilityOverride": ""
    }
  ]
}